certbot_dns_micetro/__init__.py
certbot_dns_micetro/dns_micetro.py
certbot_dns_micetro-1.0.4.dist-info/licenses/LICENSE
tests/__init__.py
certbot_dns_micetro-1.0.4.dist-info/METADATA
certbot_dns_micetro-1.0.4.dist-info/WHEEL
certbot_dns_micetro-1.0.4.dist-info/entry_points.txt
certbot_dns_micetro-1.0.4.dist-info/top_level.txt
certbot_dns_micetro-1.0.4.dist-info/RECORD
