Metadata-Version: 2.4
Name: certbot-dns-micetro
Version: 1.0.4
Summary: Certbot plugin for Micetro DNS authentication
Home-page: https://github.com/cedarville-university/certbot-dns-micetro
Author: Nat Biggs
Author-email: nbiggs112@cedarville.edu
License: Apache License 2.0
Project-URL: Bug Reports, https://github.com/cedarville-university/certbot-dns-micetro/issues
Project-URL: Source, https://github.com/cedarville-university/certbot-dns-micetro
Keywords: certbot micetro dns ssl certificate letsencrypt
Classifier: Development Status :: 4 - Beta
Classifier: Environment :: Plugins
Classifier: Intended Audience :: System Administrators
Classifier: License :: OSI Approved :: Apache Software License
Classifier: Operating System :: POSIX :: Linux
Classifier: Programming Language :: Python
Classifier: Programming Language :: Python :: 3
Classifier: Programming Language :: Python :: 3.6
Classifier: Programming Language :: Python :: 3.7
Classifier: Programming Language :: Python :: 3.8
Classifier: Programming Language :: Python :: 3.9
Classifier: Programming Language :: Python :: 3.10
Classifier: Programming Language :: Python :: 3.11
Classifier: Topic :: Internet :: WWW/HTTP
Classifier: Topic :: Security
Classifier: Topic :: System :: Installation/Setup
Classifier: Topic :: System :: Networking
Classifier: Topic :: System :: Systems Administration
Classifier: Topic :: Utilities
Requires-Python: >=3.6
License-File: LICENSE
Requires-Dist: certbot>=1.1.0
Requires-Dist: zope.interface
Requires-Dist: requests>=2.20.0
Dynamic: author
Dynamic: author-email
Dynamic: classifier
Dynamic: description
Dynamic: description-content-type
Dynamic: home-page
Dynamic: keywords
Dynamic: license
Dynamic: license-file
Dynamic: project-url
Dynamic: requires-dist
Dynamic: requires-python
Dynamic: summary
